goodreads_tools/__init__.py
goodreads_tools/__main__.py
goodreads_tools/auth/__init__.py
goodreads_tools/auth/csrf.py
goodreads_tools/auth/session.py
goodreads_tools/auth/user.py
goodreads_tools/cli.py
goodreads_tools/http_client.py
goodreads_tools/models.py
goodreads_tools/public/book.py
goodreads_tools/public/reading_chart.py
goodreads_tools/public/reading_stats.py
goodreads_tools/public/review_list.py
goodreads_tools/public/search.py
goodreads_tools/public/shelf.py
goodreads_tools/public/timeline.py
goodreads_tools-1.2.0.dist-info/WHEEL
goodreads_tools-1.2.0.dist-info/entry_points.txt
goodreads_tools-1.2.0.dist-info/METADATA
goodreads_tools-1.2.0.dist-info/RECORD
