Metadata-Version: 2.3
Name: goodreads-tools
Version: 1.2.0
Summary: Unofficial Goodreads tools for exporting reading timelines and pages/day charts.
Keywords: books,cli,dashboard,goodreads,reading,rss,scraping
Author: Evan Oman
Author-email: Evan Oman <evan058@gmail.com>
License: MIT License
Classifier: Development Status :: 3 - Alpha
Classifier: Environment :: Console
Classifier: Intended Audience :: Developers
Classifier: Intended Audience :: End Users/Desktop
Classifier: License :: OSI Approved :: MIT License
Classifier: Operating System :: OS Independent
Classifier: Programming Language :: Python :: 3
Classifier: Programming Language :: Python :: 3 :: Only
Classifier: Programming Language :: Python :: 3.12
Classifier: Programming Language :: Python :: 3.13
Classifier: Topic :: Internet
Classifier: Topic :: Utilities
Requires-Dist: browser-cookie3>=0.20.1
Requires-Dist: httpx>=0.28.1
Requires-Dist: plotext>=5.3.2
Requires-Dist: pydantic>=2.12.5
Requires-Dist: rich>=14.2.0
Requires-Dist: selectolax>=0.4.6
Requires-Dist: typer>=0.21.0
Requires-Python: >=3.13
Project-URL: Homepage, https://github.com/EvanOman/goodreads-tools
Project-URL: Issues, https://github.com/EvanOman/goodreads-tools/issues
Project-URL: Repository, https://github.com/EvanOman/goodreads-tools
